Workbook

Sheet 1-资金流转关系图
A1: 集团内部借款 · 资金流转关系图
A3: ▍一、集团股权架构
A4: 层级 | B4: 主体名称 | C4: 注册地 | D4: 角色定位 | E4: 控股方 | F4: 持股比例 | G4: 注册号/税号 | H4: 法定代表人 | I4: 备注
A5: 1 | B5: HUAFENG GROUP ENTERPRISE LIMITED（华峰集团） | C5: 中国·香港 | D5: 母公司 | E5: 方华玉 | F5: 1 | G5: 68898950（HK ） | H5: FANG HUAYU（方华玉） | I5: 集团控股平台；
A6: 2 | B6: HUATEX VIETNAM CO., LTD（华特越南） | C6: 越南·同奈 | D6: 子公司 | E6: 华峰集团 | F6: 100% | G6: 税号 3603695597 | H6: CHEN HUI（陈慧） | I6: 注册资本 51,364,560 USD，已缴足
A7: 1 | B7: WELLNAME PTE. LTD. | C7: 新加坡 | D7: 母公司 | E7: 方华珊 | F7: 1 | G7: 202313189C（ACRA） | H7: FANG HUASHAN（方华珊） | I7: Future Textile 的直接股东
A8: 2 | B8: FUTURE TEXTILE VIETNAM CO., LTD | C8: 越南·西宁 | D8: 子公司 | E8: Wellname Pte. Ltd. | F8: 100% | G8: 税号 3901352789 | H8: HUANG CHAOGUI（黄朝贵） | I8: 注册资本 617.86B VND（≈23.91M USD）
A9: 1 | B9: Suceeded Mark | D9: 母公司
A10: 2 | B10: CÔNG TY TNHH SẢN PHẨM THỂ THAO HUA XING（华星运动用品） | C10: 越南·同奈 | D10: 子公司 | E10: Suceeded Mark | F10: 1 | G10: 税号 3901240813 | H10: WANG LIGUO（王立国） | I10: 集团成员
A13: ▍二、借款资金流向
A14: 序号 | B14: 贷方（资金流出方） | C14: 借方（资金流入方） | D14: 流转层级 | E14: 币种 | F14: 合同额度 | G14: 年利率 | H14: 期限 | I14: 合同编号 / 状态
A15: 1 | B15: HUAFENG 华峰集团（香港） | C15: HUATEX 华特越南（同奈） | D15: 母公司 → 子公司 | E15: USD | F15: 10,000,000 | G15: 4%/年 | H15: 365天 | I15: 08.2025/HDV-HF-HT（旧，8/31到期）→ 08.2026/HDV-HF-HT（新）
A16: 2 | B16: WELLNAME Pte. Ltd.（新加坡） | C16: FUTURE TEXTILE VIETNAM（西宁） | D16: 母公司 → 子公司 | E16: USD | F16: 30,000,000 | G16: 4%/年 | H16: 365天 | I16: YNHT2026.07/WELL-FUTURE（2026-07-30 签署，4份正本）

Sheet 2-合同台账
A1: 集团内部借款 · 合同台账（到期提醒 + 额度使用提醒）
A2: 编制日期： | B2: =TODAY() -> 46317 | L2: 到期提醒： | Q2: 额度使用：
A3: 序号 | B3: 合同编号 | C3: 出借方 | D3: 借款方 | E3: 币种 | F3: 合同额度 | G3: 年利率 | H3: 期限(天) | I3: 签署日 | J3: 到期日 | K3: 剩余天数 | L3: 到期状态 | M3: 已提款金额 | N3: 已转股金额 | O3: 借款敞口 | P3: 剩余可用额度 | Q3: 额度使用率 | R3: 是否循环额度 | S3: FCT条款 | T3: 转股条款 | U3: 备注
A4: 1 | B4: 08.2026/HDV-HF-HT | C4: HuaFeng Group Enterprise Limited华峰企业集团（香港） | D4: Huatex（同奈） | E4: USD | F4: 10000000 | G4: 4%/年 | H4: 365 | I4: 46265 | J4: =I4+365 -> 46630 | K4: =J4-B2 -> 313 | L4: 🟢 正常 | O4: =M4-N4 -> 0 | P4: =IF(R4="是",F4-O4,F4-M4) -> 10000000 | Q4: =IF(R4="是",O4/F4,M4/F4) -> 0 | R4: 是 | S4: FCT 全部由借方承担 | T4: 本金+已产生利息一并转股 | U4: 2份正本，各持1份
A5: 2 | B5: YNHT2026.07/WELL-FUTURE | C5: Wellname Pte. Ltd.（新加坡） | D5: Future Textile（西宁） | E5: USD | F5: 30000000 | G5: 4%/年 | H5: 365 | I5: 46233 | J5: 46598 | K5: =J5-B2 -> 281 | L5: 🟢 正常 | M5: =SUM('3-提款明细'!F20:F28) -> 27449000 | O5: =M5-N5 -> 27449000 | P5: =IF(R5="是",F5-O5,F5-M5) -> 2551000 | Q5: =IF(R5="是",O5/F5,M5/F5) -> 0.91496667 | R5: 是 | S5: FCT 全部由借方承担 | T5: 本金+已产生利息一并转股 | U5: 4份正本，各持2份
A6: 3 | B6: YNHT2025.11/WILL-FUTURE | C6: Wellname Pte. Ltd.（新加坡） | D6: Future Textile（西宁） | E6: USD | F6: 20000000 | G6: 4%/年 | H6: 365 | I6: 45991 | J6: =I6+H6 -> 46356 | K6: =J6-B2 -> 39 | L6: 🟢 正常 | M6: =SUM('3-提款明细'!F34:F56) -> 19770000 | N6: =SUM('3-提款明细'!F34:F42) -> 11940000 | O6: =M6-N6 -> 7830000 | P6: =IF(R6="是",F6-O6,F6-M6) -> 230000 | Q6: =M6/F6 -> 0.9885 | R6: 否 | S6: 无 | T6: 本金可转股 | U6: 3份正本，各持1份，剩余1份给银行
A7: 4 | B7: YNHT2026.10/WELL-FUTURE | C7: Wellname Pte. Ltd.（新加坡） | D7: Future Textile（西宁） | E7: USD | F7: 50000000 | G7: 4%/年 | H7: 365 | I7: 46310 | J7: 46675 | K7: =J7-B2 -> 358 | L7: 🟢 正常 | O7: =M7-N7 -> 0 | P7: =IF(R7="是",F7-O7,F7-M7) -> 50000000 | Q7: =M7/F7 -> 0 | R7: 否 | S7: FCT 全部由借方承担 | T7: 本金+已产生利息一并转股 | U7: 4份正本，各持2份
A8: 5 | B8: 04.2026/HDV-JGLI-KD | C8: Jinguangli International Limited | D8: Khoa Dung（西宁） | E8: USD | F8: 20000000 | G8: 4%/年 | H8: 360 | I8: 46142 | J8: =I8+H8 -> 46502 | K8: =J8-B2 -> 185 | L8: 🟢 正常 | M8: =SUM('3-提款明细'!F75:F78) -> 1650000 | O8: =M8-N8 -> 1650000 | P8: =IF(R8="是",F8-O8,F8-M8) -> 18350000 | Q8: =IF(R8="是",O8/F8,M8/F8) -> 0.0825 | R8: 是 | S8: FCT 全部由借方承担 | T8: 本金+已产生利息一并转股 | U8: 4份正本，各持2份
A9: 合计敞口 | F9: =SUM(F4:F8) -> 130000000 | M9: =SUM(M4:M8) -> 48869000 | N9: =SUM(N4:N8) -> 11940000 | O9: =SUM(O4:O8) -> 36929000 | P9: =SUM(P4:P8) -> 81131000 | Q9: =M9/F9 -> 0.37591538

Sheet 3-提款明细
A1: ='2-合同台账'!B4 -> 08.2026/HDV-HF-HT
A2: 资金组织 | B2: 账户所属组织 | C2: 登账日期 | D2: 对方名称 | E2: 币种 | F2: 支出金额
A18: ='2-合同台账'!B5 -> YNHT2026.07/WELL-FUTURE
A19: 资金组织 | B19: 账户所属组织 | C19: 登账日期 | D19: 对方名称 | E19: 币种 | F19: 支出金额
A20: WELLNAME PTE. LTD. | B20: WELLNAME PTE. LTD. | C20: 46261 | D20: VIET NAM FUTURE TEXTILE COMPANY LIMITED | E20: 美元 | F20: 500000
A21: WELLNAME PTE. LTD. | B21: WELLNAME PTE. LTD. | C21: 46272 | D21: VIET NAM FUTURE TEXTILE COMPANY LIMITED | E21: 美元 | F21: 100000
A22: WELLNAME PTE. LTD. | B22: WELLNAME PTE. LTD. | C22: 46288 | D22: VIET NAM FUTURE TEXTILE COMPANY LIMITED | E22: 美元 | F22: 200000
A23: WELLNAME PTE. LTD. | B23: WELLNAME PTE. LTD. | C23: 46293 | D23: VIET NAM FUTURE TEXTILE COMPANY LIMITED | E23: 美元 | F23: 500000
A24: WELLNAME PTE. LTD. | B24: WELLNAME PTE. LTD. | C24: 46301 | D24: VIET NAM FUTURE TEXTILE COMPANY LIMITED | E24: 美元 | F24: 3639000
A25: WELLNAME PTE. LTD. | B25: WELLNAME PTE. LTD. | C25: 46308 | D25: VIET NAM FUTURE TEXTILE COMPANY LIMITED | E25: 美元 | F25: 5500000
A26: WELLNAME PTE. LTD. | B26: WELLNAME PTE. LTD. | C26: 46311 | D26: VIET NAM FUTURE TEXTILE COMPANY LIMITED | E26: 美元 | F26: 6000000
A27: WELLNAME PTE. LTD. | B27: WELLNAME PTE. LTD. | C27: 46311 | D27: VIET NAM FUTURE TEXTILE COMPANY LIMITED | E27: 美元 | F27: 3500000
A28: WELLNAME PTE. LTD. | B28: WELLNAME PTE. LTD. | C28: 46316 | E28: 美元 | F28: 7510000
A32: ='2-合同台账'!B6 -> YNHT2025.11/WILL-FUTURE
A33: 资金组织 | B33: 账户所属组织 | C33: 登账日期 | D33: 对方名称 | E33: 币种 | F33: 支出金额
A34: VIET NAM FUTURE TEXTILE COMPANY LIMITED | B34: VIET NAM FUTURE TEXTILE COMPANY LIMITED | C34: 45978 | D34: WELLNAME PTE. LTD. | E34: 美元 | F34: 2840000
A35: VIET NAM FUTURE TEXTILE COMPANY LIMITED | B35: VIET NAM FUTURE TEXTILE COMPANY LIMITED | C35: 45978 | D35: WELLNAME PTE. LTD. | E35: 美元 | F35: 1000000
A36: VIET NAM FUTURE TEXTILE COMPANY LIMITED | B36: VIET NAM FUTURE TEXTILE COMPANY LIMITED | C36: 45985 | D36: WELLNAME PTE. LTD. | E36: 美元 | F36: 70000
A37: VIET NAM FUTURE TEXTILE COMPANY LIMITED | B37: VIET NAM FUTURE TEXTILE COMPANY LIMITED | C37: 45989 | D37: WELLNAME PTE. LTD. | E37: 美元 | F37: 500000
A38: VIET NAM FUTURE TEXTILE COMPANY LIMITED | B38: VIET NAM FUTURE TEXTILE COMPANY LIMITED | C38: 45993 | D38: WELLNAME PTE. LTD. | E38: 美元 | F38: 500000
A39: VIET NAM FUTURE TEXTILE COMPANY LIMITED | B39: VIET NAM FUTURE TEXTILE COMPANY LIMITED | C39: 46007 | D39: WELLNAME PTE. LTD. | E39: 美元 | F39: 450000
A40: VIET NAM FUTURE TEXTILE COMPANY LIMITED | B40: VIET NAM FUTURE TEXTILE COMPANY LIMITED | C40: 46014 | D40: WELLNAME PTE. LTD. | E40: 美元 | F40: 500000
A41: VIET NAM FUTURE TEXTILE COMPANY LIMITED | B41: VIET NAM FUTURE TEXTILE COMPANY LIMITED | C41: 46028 | D41: WELLNAME PTE. LTD. | E41: 美元 | F41: 1890000
A42: VIET NAM FUTURE TEXTILE COMPANY LIMITED | B42: VIET NAM FUTURE TEXTILE COMPANY LIMITED | C42: 46029 | D42: WELLNAME PTE. LTD. | E42: 美元 | F42: 4190000
A43: VIET NAM FUTURE TEXTILE COMPANY LIMITED | B43: VIET NAM FUTURE TEXTILE COMPANY LIMITED | C43: 46098 | D43: WELLNAME PTE. LTD. | E43: 美元 | F43: 100000
A44: VIET NAM FUTURE TEXTILE COMPANY LIMITED | B44: VIET NAM FUTURE TEXTILE COMPANY LIMITED | C44: 46121 | D44: WELLNAME PTE. LTD. | E44: 美元 | F44: 1000000
A45: VIET NAM FUTURE TEXTILE COMPANY LIMITED | B45: VIET NAM FUTURE TEXTILE COMPANY LIMITED | C45: 46129 | D45: WELLNAME PTE. LTD. | E45: 美元 | F45: 450000
... A56: VIET NAM FUTURE TEXTILE COMPANY LIMITED | B56: VIET NAM FUTURE TEXTILE COMPANY LIMITED | C56: 46246 | D56: WELLNAME PTE. LTD. | E56: 美元 | F56: 400000
A60: ='2-合同台账'!B7 -> YNHT2026.10/WELL-FUTURE
A61: 资金组织 | B61: 账户所属组织 | C61: 登账日期 | D61: 对方名称 | E61: 币种 | F61: 支出金额
A73: ='2-合同台账'!B8 -> 04.2026/HDV-JGLI-KD
A74: 资金组织 | B74: 账户所属组织 | C74: 登账日期 | D74: 对方名称 | E74: 币种 | F74: 支出金额
A75: JINGUANGLI INTERNATIONAL LIMITED | C75: 2026/05/14 | D75: KHOA DUNG | E75: 美元 | F75: 50000
A76: JINGUANGLI INTERNATIONAL LIMITED | C76: 2026/05/18 | D76: KHOA DUNG | E76: 美元 | F76: 300000
A77: JINGUANGLI INTERNATIONAL LIMITED | C77: 46170 | D77: KHOA DUNG | E77: 美元 | F77: 600000
A78: JINGUANGLI INTERNATIONAL LIMITED | C78: 46312 | D78: KHOA DUNG | E78: 美元 | F78: 700000
